LICENSE.txt
MANIFEST.in
README.md
pytest.ini
setup.py
gmdata_webinterface/__init__.py
gmdata_webinterface/consume_rest.ini
gmdata_webinterface/consume_webservices.py
gmdata_webinterface/sandboxed_format.py
gmdata_webinterface.egg-info/PKG-INFO
gmdata_webinterface.egg-info/SOURCES.txt
gmdata_webinterface.egg-info/dependency_links.txt
gmdata_webinterface.egg-info/not-zip-safe
gmdata_webinterface.egg-info/requires.txt
gmdata_webinterface.egg-info/top_level.txt
gmdata_webinterface/tests/__init__.py
gmdata_webinterface/tests/datarequest_tests.py
gmdata_webinterface/tests/formdata_tests.py
gmdata_webinterface/tests/functional_tests.py
gmdata_webinterface/tests/parsed_config_file_tests.py
gmdata_webinterface/tests/test_data/wdc_minute_data_iaga2002output.ini
gmdata_webinterface/tests/test_data/wdc_minute_data_wdcoutput.ini
gmdata_webinterface/tests/test_data/known_good/README_KNOWN_GOOD_DATA.md
gmdata_webinterface/tests/test_data/known_good/esk201501dmin.min
gmdata_webinterface/tests/test_data/known_good/esk201502dmin.min
gmdata_webinterface/tests/test_data/known_good/esk201503dmin.min
gmdata_webinterface/tests/test_data/known_good/esk201504dmin.min
gmdata_webinterface/tests/test_data/known_good/esk201505dmin.min
gmdata_webinterface/tests/test_data/known_good/esk201506dmin.min
gmdata_webinterface/tests/test_data/known_good/esk201507dmin.min
gmdata_webinterface/tests/test_data/known_good/esk201508dmin.min
gmdata_webinterface/tests/test_data/known_good/esk201509dmin.min
gmdata_webinterface/tests/test_data/known_good/esk201510dmin.min
gmdata_webinterface/tests/test_data/known_good/esk201511dmin.min
gmdata_webinterface/tests/test_data/known_good/esk201512dmin.min
gmdata_webinterface/tests/test_data/known_good/ngk2015.wdc