Metadata-Version: 1.2
Name: gmdata-webinterface
Version: 1.0.7
Summary: Retrieve geomagnetic observatory data via web services
Home-page: https://github.com/willjbrown88/geomag_wdc_web_app_interface
Author: W. Brown
Author-email: wb@bgs.ac.uk
License: MIT
Keywords: geomagnetism,geomagnetic observatory data,wdc,intermagnet
Platform: UNKNOWN
Classifier: Programming Language :: Python :: 3
Requires-Python: >=3.4
